tests/voxelment/__init__.py
tests/voxelment/augmentations/__init__.py
tests/voxelment/augmentations/test_functional.py
tests/voxelment/augmentations/test_misc.py
tests/voxelment/augmentations/test_transforms.py
tests/voxelment/augmentations/filter/__init__.py
tests/voxelment/augmentations/filter/test_transforms.py
tests/voxelment/augmentations/time/__init__.py
tests/voxelment/augmentations/time/test_functional.py
tests/voxelment/augmentations/time/test_transforms.py
tests/voxelment/core/__init__.py
tests/voxelment/core/test_compositions.py
tests/voxelment/core/test_transforms.py
tests/voxelmentations/__init__.py
tests/voxelmentations/augmentations/__init__.py
tests/voxelmentations/augmentations/test_functional.py
tests/voxelmentations/augmentations/test_misc.py
tests/voxelmentations/augmentations/test_transforms.py
tests/voxelmentations/core/__init__.py
tests/voxelmentations/core/test_compositions.py
tests/voxelmentations/core/test_functional.py
tests/voxelmentations/core/test_transforms.py
voxelment/__init__.py
voxelment/__version__.py
voxelment/augmentations/__init__.py
voxelment/augmentations/enum.py
voxelment/augmentations/functional.py
voxelment/augmentations/misc.py
voxelment/augmentations/transforms.py
voxelment/augmentations/filter/__init__.py
voxelment/augmentations/filter/functional.py
voxelment/augmentations/filter/transforms.py
voxelment/augmentations/time/__init__.py
voxelment/augmentations/time/functional.py
voxelment/augmentations/time/transforms.py
voxelment/core/__init__.py
voxelment/core/application.py
voxelment/core/compositions.py
voxelment/core/transforms.py
voxelment/core/utils.py
voxelmentations/__init__.py
voxelmentations/__version__.py
voxelmentations/augmentations/__init__.py
voxelmentations/augmentations/enum.py
voxelmentations/augmentations/functional.py
voxelmentations/augmentations/misc.py
voxelmentations/augmentations/transforms.py
voxelmentations/core/__init__.py
voxelmentations/core/application.py
voxelmentations-0.0.1.dist-info/LICENSE
voxelmentations-0.0.1.dist-info/METADATA
voxelmentations-0.0.1.dist-info/WHEEL
voxelmentations-0.0.1.dist-info/top_level.txt
voxelmentations-0.0.1.dist-info/RECORD
