Metadata-Version: 2.1
Name: voxelmentations
Version: 0.0.1
Summary: A PyTorch library for augmentations of 3d data.
Home-page: https://github.com/rostepifanov/voxelmentations
Download-URL: https://github.com/rostepifanov/voxelmentations/tags
Author: Rostislav Epifanov
Author-email: rostepifanov@gmail.com
License: MIT
Keywords: voxelmentations,augmentation,deep learning,three dimensional data
Classifier: Development Status :: 4 - Beta
Classifier: Intended Audience :: Developers
Classifier: Intended Audience :: Education
Classifier: Intended Audience :: Science/Research
Classifier: License :: OSI Approved :: MIT License
Classifier: Operating System :: OS Independent
Classifier: Topic :: Scientific/Engineering
Classifier: Topic :: Scientific/Engineering :: Mathematics
Classifier: Topic :: Scientific/Engineering :: Artificial Intelligence
Classifier: Topic :: Software Development
Classifier: Topic :: Software Development :: Libraries
Classifier: Topic :: Software Development :: Libraries :: Python Modules
Classifier: Programming Language :: Python
Classifier: Programming Language :: Python :: 3
Classifier: Programming Language :: Python :: 3.7
Classifier: Programming Language :: Python :: 3.8
Classifier: Programming Language :: Python :: 3.9
Classifier: Programming Language :: Python :: 3.10
Classifier: Programming Language :: Python :: 3.11
Requires-Python: >=3.7.0
License-File: LICENSE
Requires-Dist: numpy >=1.20.0
Requires-Dist: scipy >=1.10.1
Requires-Dist: opencv-python-headless >=4.1.1
Provides-Extra: tests
Requires-Dist: pytest ; extra == 'tests'
